{
    "text": [
        "Find the structure characterized by its vertical stripes and subdued colors seen through the mist.",
        "Identify the edifice with vertical patterns and a toned-down palette that can be seen through the fog.",
        "Spot the construction distinguished by its upright lines and soft hues visible through the haze."
    ],
    "is_sentence": true,
    "shapes": [
        {
            "label": "target",
            "labels": [
                "target"
            ],
            "shape_type": "polygon",
            "image_name": "lisat_gres_000000025278.jpg",
            "points": [
                [
                    131.0,
                    390.0
                ],
                [
                    131.0,
                    392.0
                ],
                [
                    130.0,
                    392.0
                ],
                [
                    130.0,
                    395.0
                ],
                [
                    132.0,
                    395.0
                ],
                [
                    132.0,
                    390.0
                ],
                [
                    131.0,
                    390.0
                ],
                [
                    138.0,
                    400.0
                ],
                [
                    138.0,
                    401.0
                ],
                [
                    137.0,
                    401.0
                ],
                [
                    137.0,
                    402.0
                ],
                [
                    138.0,
                    402.0
                ],
                [
                    138.0,
                    405.0
                ],
                [
                    140.0,
                    405.0
                ],
                [
                    140.0,
                    400.0
                ],
                [
                    138.0,
                    400.0
                ],
                [
                    256.0,
                    408.0
                ],
                [
                    256.0,
                    411.0
                ],
                [
                    258.0,
                    411.0
                ],
                [
                    258.0,
                    410.0
                ],
                [
                    260.0,
                    410.0
                ],
                [
                    260.0,
                    409.0
                ],
                [
                    259.0,
                    409.0
                ],
                [
                    259.0,
                    408.0
                ],
                [
                    256.0,
                    408.0
                ],
                [
                    287.0,
                    402.0
                ],
                [
                    287.0,
                    403.0
                ],
                [
                    286.0,
                    403.0
                ],
                [
                    286.0,
                    404.0
                ],
                [
                    284.0,
                    404.0
                ],
                [
                    284.0,
                    403.0
                ],
                [
                    282.0,
                    403.0
                ],
                [
                    282.0,
                    404.0
                ],
                [
                    280.0,
                    404.0
                ],
                [
                    280.0,
                    407.0
                ],
                [
                    279.0,
                    407.0
                ],
                [
                    279.0,
                    408.0
                ],
                [
                    274.0,
                    408.0
                ],
                [
                    274.0,
                    409.0
                ],
                [
                    272.0,
                    409.0
                ],
                [
                    272.0,
                    410.0
                ],
                [
                    273.0,
                    410.0
                ],
                [
                    273.0,
                    411.0
                ],
                [
                    274.0,
                    411.0
                ],
                [
                    274.0,
                    413.0
                ],
                [
                    280.0,
                    413.0
                ],
                [
                    280.0,
                    414.0
                ],
                [
                    281.0,
                    414.0
                ],
                [
                    281.0,
                    415.0
                ],
                [
                    284.0,
                    415.0
                ],
                [
                    284.0,
                    414.0
                ],
                [
                    299.0,
                    414.0
                ],
                [
                    299.0,
                    413.0
                ],
                [
                    302.0,
                    413.0
                ],
                [
                    302.0,
                    412.0
                ],
                [
                    304.0,
                    412.0
                ],
                [
                    304.0,
                    413.0
                ],
                [
                    306.0,
                    413.0
                ],
                [
                    306.0,
                    412.0
                ],
                [
                    312.0,
                    412.0
                ],
                [
                    312.0,
                    413.0
                ],
                [
                    314.0,
                    413.0
                ],
                [
                    314.0,
                    412.0
                ],
                [
                    316.0,
                    412.0
                ],
                [
                    316.0,
                    408.0
                ],
                [
                    315.0,
                    408.0
                ],
                [
                    315.0,
                    402.0
                ],
                [
                    312.0,
                    402.0
                ],
                [
                    312.0,
                    407.0
                ],
                [
                    310.0,
                    407.0
                ],
                [
                    310.0,
                    408.0
                ],
                [
                    308.0,
                    408.0
                ],
                [
                    308.0,
                    407.0
                ],
                [
                    307.0,
                    407.0
                ],
                [
                    307.0,
                    404.0
                ],
                [
                    308.0,
                    404.0
                ],
                [
                    308.0,
                    403.0
                ],
                [
                    307.0,
                    403.0
                ],
                [
                    307.0,
                    402.0
                ],
                [
                    306.0,
                    402.0
                ],
                [
                    306.0,
                    403.0
                ],
                [
                    305.0,
                    403.0
                ],
                [
                    305.0,
                    405.0
                ],
                [
                    306.0,
                    405.0
                ],
                [
                    306.0,
                    407.0
                ],
                [
                    304.0,
                    407.0
                ],
                [
                    304.0,
                    408.0
                ],
                [
                    300.0,
                    408.0
                ],
                [
                    300.0,
                    403.0
                ],
                [
                    296.0,
                    403.0
                ],
                [
                    296.0,
                    402.0
                ],
                [
                    294.0,
                    402.0
                ],
                [
                    294.0,
                    403.0
                ],
                [
                    292.0,
                    403.0
                ],
                [
                    292.0,
                    402.0
                ],
                [
                    287.0,
                    402.0
                ],
                [
                    312.0,
                    417.0
                ],
                [
                    312.0,
                    418.0
                ],
                [
                    313.0,
                    418.0
                ],
                [
                    313.0,
                    419.0
                ],
                [
                    314.0,
                    419.0
                ],
                [
                    314.0,
                    417.0
                ],
                [
                    312.0,
                    417.0
                ],
                [
                    249.0,
                    417.0
                ],
                [
                    249.0,
                    419.0
                ],
                [
                    250.0,
                    419.0
                ],
                [
                    250.0,
                    420.0
                ],
                [
                    251.0,
                    420.0
                ],
                [
                    251.0,
                    419.0
                ],
                [
                    252.0,
                    419.0
                ],
                [
                    252.0,
                    417.0
                ],
                [
                    249.0,
                    417.0
                ],
                [
                    3.0,
                    229.0
                ],
                [
                    3.0,
                    230.0
                ],
                [
                    2.0,
                    230.0
                ],
                [
                    2.0,
                    234.0
                ],
                [
                    1.0,
                    234.0
                ],
                [
                    1.0,
                    238.0
                ],
                [
                    0.0,
                    238.0
                ],
                [
                    0.0,
                    252.0
                ],
                [
                    1.0,
                    252.0
                ],
                [
                    1.0,
                    257.0
                ],
                [
                    0.0,
                    257.0
                ],
                [
                    0.0,
                    261.0
                ],
                [
                    1.0,
                    261.0
                ],
                [
                    1.0,
                    262.0
                ],
                [
                    0.0,
                    262.0
                ],
                [
                    0.0,
                    305.0
                ],
                [
                    1.0,
                    305.0
                ],
                [
                    1.0,
                    312.0
                ],
                [
                    0.0,
                    312.0
                ],
                [
                    0.0,
                    314.0
                ],
                [
                    1.0,
                    314.0
                ],
                [
                    1.0,
                    328.0
                ],
                [
                    0.0,
                    328.0
                ],
                [
                    0.0,
                    354.0
                ],
                [
                    2.0,
                    354.0
                ],
                [
                    2.0,
                    357.0
                ],
                [
                    3.0,
                    357.0
                ],
                [
                    3.0,
                    358.0
                ],
                [
                    2.0,
                    358.0
                ],
                [
                    2.0,
                    361.0
                ],
                [
                    1.0,
                    361.0
                ],
                [
                    1.0,
                    362.0
                ],
                [
                    2.0,
                    362.0
                ],
                [
                    2.0,
                    366.0
                ],
                [
                    3.0,
                    366.0
                ],
                [
                    3.0,
                    368.0
                ],
                [
                    2.0,
                    368.0
                ],
                [
                    2.0,
                    392.0
                ],
                [
                    1.0,
                    392.0
                ],
                [
                    1.0,
                    393.0
                ],
                [
                    2.0,
                    393.0
                ],
                [
                    2.0,
                    395.0
                ],
                [
                    5.0,
                    395.0
                ],
                [
                    5.0,
                    396.0
                ],
                [
                    11.0,
                    396.0
                ],
                [
                    11.0,
                    397.0
                ],
                [
                    17.0,
                    397.0
                ],
                [
                    17.0,
                    398.0
                ],
                [
                    26.0,
                    398.0
                ],
                [
                    26.0,
                    399.0
                ],
                [
                    33.0,
                    399.0
                ],
                [
                    33.0,
                    400.0
                ],
                [
                    38.0,
                    400.0
                ],
                [
                    38.0,
                    401.0
                ],
                [
                    42.0,
                    401.0
                ],
                [
                    42.0,
                    402.0
                ],
                [
                    53.0,
                    402.0
                ],
                [
                    53.0,
                    403.0
                ],
                [
                    58.0,
                    403.0
                ],
                [
                    58.0,
                    404.0
                ],
                [
                    65.0,
                    404.0
                ],
                [
                    65.0,
                    405.0
                ],
                [
                    69.0,
                    405.0
                ],
                [
                    69.0,
                    406.0
                ],
                [
                    83.0,
                    406.0
                ],
                [
                    83.0,
                    407.0
                ],
                [
                    90.0,
                    407.0
                ],
                [
                    90.0,
                    408.0
                ],
                [
                    93.0,
                    408.0
                ],
                [
                    93.0,
                    409.0
                ],
                [
                    95.0,
                    409.0
                ],
                [
                    95.0,
                    410.0
                ],
                [
                    106.0,
                    410.0
                ],
                [
                    106.0,
                    411.0
                ],
                [
                    114.0,
                    411.0
                ],
                [
                    114.0,
                    412.0
                ],
                [
                    118.0,
                    412.0
                ],
                [
                    118.0,
                    413.0
                ],
                [
                    120.0,
                    413.0
                ],
                [
                    120.0,
                    412.0
                ],
                [
                    122.0,
                    412.0
                ],
                [
                    122.0,
                    413.0
                ],
                [
                    125.0,
                    413.0
                ],
                [
                    125.0,
                    414.0
                ],
                [
                    128.0,
                    414.0
                ],
                [
                    128.0,
                    413.0
                ],
                [
                    131.0,
                    413.0
                ],
                [
                    131.0,
                    414.0
                ],
                [
                    132.0,
                    414.0
                ],
                [
                    132.0,
                    413.0
                ],
                [
                    133.0,
                    413.0
                ],
                [
                    133.0,
                    414.0
                ],
                [
                    136.0,
                    414.0
                ],
                [
                    136.0,
                    413.0
                ],
                [
                    138.0,
                    413.0
                ],
                [
                    138.0,
                    414.0
                ],
                [
                    139.0,
                    414.0
                ],
                [
                    139.0,
                    413.0
                ],
                [
                    140.0,
                    413.0
                ],
                [
                    140.0,
                    408.0
                ],
                [
                    138.0,
                    408.0
                ],
                [
                    138.0,
                    412.0
                ],
                [
                    136.0,
                    412.0
                ],
                [
                    136.0,
                    400.0
                ],
                [
                    135.0,
                    400.0
                ],
                [
                    135.0,
                    401.0
                ],
                [
                    134.0,
                    401.0
                ],
                [
                    134.0,
                    407.0
                ],
                [
                    133.0,
                    407.0
                ],
                [
                    133.0,
                    408.0
                ],
                [
                    132.0,
                    408.0
                ],
                [
                    132.0,
                    400.0
                ],
                [
                    130.0,
                    400.0
                ],
                [
                    130.0,
                    401.0
                ],
                [
                    129.0,
                    401.0
                ],
                [
                    129.0,
                    400.0
                ],
                [
                    128.0,
                    400.0
                ],
                [
                    128.0,
                    394.0
                ],
                [
                    129.0,
                    394.0
                ],
                [
                    129.0,
                    392.0
                ],
                [
                    128.0,
                    392.0
                ],
                [
                    128.0,
                    387.0
                ],
                [
                    129.0,
                    387.0
                ],
                [
                    129.0,
                    386.0
                ],
                [
                    130.0,
                    386.0
                ],
                [
                    130.0,
                    388.0
                ],
                [
                    131.0,
                    388.0
                ],
                [
                    131.0,
                    389.0
                ],
                [
                    133.0,
                    389.0
                ],
                [
                    133.0,
                    392.0
                ],
                [
                    134.0,
                    392.0
                ],
                [
                    134.0,
                    398.0
                ],
                [
                    135.0,
                    398.0
                ],
                [
                    135.0,
                    397.0
                ],
                [
                    136.0,
                    397.0
                ],
                [
                    136.0,
                    394.0
                ],
                [
                    138.0,
                    394.0
                ],
                [
                    138.0,
                    397.0
                ],
                [
                    139.0,
                    397.0
                ],
                [
                    139.0,
                    398.0
                ],
                [
                    140.0,
                    398.0
                ],
                [
                    140.0,
                    391.0
                ],
                [
                    138.0,
                    391.0
                ],
                [
                    138.0,
                    392.0
                ],
                [
                    136.0,
                    392.0
                ],
                [
                    136.0,
                    388.0
                ],
                [
                    138.0,
                    388.0
                ],
                [
                    138.0,
                    389.0
                ],
                [
                    139.0,
                    389.0
                ],
                [
                    139.0,
                    390.0
                ],
                [
                    140.0,
                    390.0
                ],
                [
                    140.0,
                    389.0
                ],
                [
                    145.0,
                    389.0
                ],
                [
                    145.0,
                    390.0
                ],
                [
                    146.0,
                    390.0
                ],
                [
                    146.0,
                    392.0
                ],
                [
                    143.0,
                    392.0
                ],
                [
                    143.0,
                    395.0
                ],
                [
                    144.0,
                    395.0
                ],
                [
                    144.0,
                    394.0
                ],
                [
                    145.0,
                    394.0
                ],
                [
                    145.0,
                    398.0
                ],
                [
                    146.0,
                    398.0
                ],
                [
                    146.0,
                    400.0
                ],
                [
                    143.0,
                    400.0
                ],
                [
                    143.0,
                    402.0
                ],
                [
                    145.0,
                    402.0
                ],
                [
                    145.0,
                    406.0
                ],
                [
                    146.0,
                    406.0
                ],
                [
                    146.0,
                    408.0
                ],
                [
                    144.0,
                    408.0
                ],
                [
                    144.0,
                    410.0
                ],
                [
                    145.0,
                    410.0
                ],
                [
                    145.0,
                    414.0
                ],
                [
                    146.0,
                    414.0
                ],
                [
                    146.0,
                    415.0
                ],
                [
                    148.0,
                    415.0
                ],
                [
                    148.0,
                    416.0
                ],
                [
                    150.0,
                    416.0
                ],
                [
                    150.0,
                    417.0
                ],
                [
                    154.0,
                    417.0
                ],
                [
                    154.0,
                    418.0
                ],
                [
                    166.0,
                    418.0
                ],
                [
                    166.0,
                    419.0
                ],
                [
                    173.0,
                    419.0
                ],
                [
                    173.0,
                    420.0
                ],
                [
                    176.0,
                    420.0
                ],
                [
                    176.0,
                    419.0
                ],
                [
                    178.0,
                    419.0
                ],
                [
                    178.0,
                    420.0
                ],
                [
                    186.0,
                    420.0
                ],
                [
                    186.0,
                    421.0
                ],
                [
                    188.0,
                    421.0
                ],
                [
                    188.0,
                    420.0
                ],
                [
                    190.0,
                    420.0
                ],
                [
                    190.0,
                    419.0
                ],
                [
                    194.0,
                    419.0
                ],
                [
                    194.0,
                    420.0
                ],
                [
                    195.0,
                    420.0
                ],
                [
                    195.0,
                    421.0
                ],
                [
                    196.0,
                    421.0
                ],
                [
                    196.0,
                    420.0
                ],
                [
                    198.0,
                    420.0
                ],
                [
                    198.0,
                    421.0
                ],
                [
                    204.0,
                    421.0
                ],
                [
                    204.0,
                    420.0
                ],
                [
                    208.0,
                    420.0
                ],
                [
                    208.0,
                    419.0
                ],
                [
                    209.0,
                    419.0
                ],
                [
                    209.0,
                    420.0
                ],
                [
                    211.0,
                    420.0
                ],
                [
                    211.0,
                    421.0
                ],
                [
                    212.0,
                    421.0
                ],
                [
                    212.0,
                    420.0
                ],
                [
                    214.0,
                    420.0
                ],
                [
                    214.0,
                    421.0
                ],
                [
                    217.0,
                    421.0
                ],
                [
                    217.0,
                    420.0
                ],
                [
                    218.0,
                    420.0
                ],
                [
                    218.0,
                    421.0
                ],
                [
                    219.0,
                    421.0
                ],
                [
                    219.0,
                    420.0
                ],
                [
                    220.0,
                    420.0
                ],
                [
                    220.0,
                    419.0
                ],
                [
                    222.0,
                    419.0
                ],
                [
                    222.0,
                    418.0
                ],
                [
                    224.0,
                    418.0
                ],
                [
                    224.0,
                    417.0
                ],
                [
                    232.0,
                    417.0
                ],
                [
                    232.0,
                    416.0
                ],
                [
                    233.0,
                    416.0
                ],
                [
                    233.0,
                    415.0
                ],
                [
                    236.0,
                    415.0
                ],
                [
                    236.0,
                    414.0
                ],
                [
                    241.0,
                    414.0
                ],
                [
                    241.0,
                    413.0
                ],
                [
                    244.0,
                    413.0
                ],
                [
                    244.0,
                    412.0
                ],
                [
                    248.0,
                    412.0
                ],
                [
                    248.0,
                    413.0
                ],
                [
                    251.0,
                    413.0
                ],
                [
                    251.0,
                    412.0
                ],
                [
                    252.0,
                    412.0
                ],
                [
                    252.0,
                    411.0
                ],
                [
                    253.0,
                    411.0
                ],
                [
                    253.0,
                    408.0
                ],
                [
                    252.0,
                    408.0
                ],
                [
                    252.0,
                    405.0
                ],
                [
                    253.0,
                    405.0
                ],
                [
                    253.0,
                    403.0
                ],
                [
                    254.0,
                    403.0
                ],
                [
                    254.0,
                    401.0
                ],
                [
                    255.0,
                    401.0
                ],
                [
                    255.0,
                    402.0
                ],
                [
                    256.0,
                    402.0
                ],
                [
                    256.0,
                    406.0
                ],
                [
                    259.0,
                    406.0
                ],
                [
                    259.0,
                    405.0
                ],
                [
                    264.0,
                    405.0
                ],
                [
                    264.0,
                    407.0
                ],
                [
                    265.0,
                    407.0
                ],
                [
                    265.0,
                    408.0
                ],
                [
                    264.0,
                    408.0
                ],
                [
                    264.0,
                    412.0
                ],
                [
                    265.0,
                    412.0
                ],
                [
                    265.0,
                    413.0
                ],
                [
                    270.0,
                    413.0
                ],
                [
                    270.0,
                    410.0
                ],
                [
                    271.0,
                    410.0
                ],
                [
                    271.0,
                    408.0
                ],
                [
                    270.0,
                    408.0
                ],
                [
                    270.0,
                    406.0
                ],
                [
                    271.0,
                    406.0
                ],
                [
                    271.0,
                    405.0
                ],
                [
                    272.0,
                    405.0
                ],
                [
                    272.0,
                    401.0
                ],
                [
                    273.0,
                    401.0
                ],
                [
                    273.0,
                    400.0
                ],
                [
                    289.0,
                    400.0
                ],
                [
                    289.0,
                    401.0
                ],
                [
                    290.0,
                    401.0
                ],
                [
                    290.0,
                    400.0
                ],
                [
                    302.0,
                    400.0
                ],
                [
                    302.0,
                    399.0
                ],
                [
                    303.0,
                    399.0
                ],
                [
                    303.0,
                    400.0
                ],
                [
                    312.0,
                    400.0
                ],
                [
                    312.0,
                    401.0
                ],
                [
                    314.0,
                    401.0
                ],
                [
                    314.0,
                    400.0
                ],
                [
                    316.0,
                    400.0
                ],
                [
                    316.0,
                    397.0
                ],
                [
                    317.0,
                    397.0
                ],
                [
                    317.0,
                    388.0
                ],
                [
                    318.0,
                    388.0
                ],
                [
                    318.0,
                    384.0
                ],
                [
                    317.0,
                    384.0
                ],
                [
                    317.0,
                    381.0
                ],
                [
                    318.0,
                    381.0
                ],
                [
                    318.0,
                    371.0
                ],
                [
                    319.0,
                    371.0
                ],
                [
                    319.0,
                    355.0
                ],
                [
                    320.0,
                    355.0
                ],
                [
                    320.0,
                    350.0
                ],
                [
                    319.0,
                    350.0
                ],
                [
                    319.0,
                    348.0
                ],
                [
                    320.0,
                    348.0
                ],
                [
                    320.0,
                    342.0
                ],
                [
                    319.0,
                    342.0
                ],
                [
                    319.0,
                    340.0
                ],
                [
                    320.0,
                    340.0
                ],
                [
                    320.0,
                    338.0
                ],
                [
                    319.0,
                    338.0
                ],
                [
                    319.0,
                    304.0
                ],
                [
                    318.0,
                    304.0
                ],
                [
                    318.0,
                    280.0
                ],
                [
                    317.0,
                    280.0
                ],
                [
                    317.0,
                    275.0
                ],
                [
                    316.0,
                    275.0
                ],
                [
                    316.0,
                    274.0
                ],
                [
                    310.0,
                    274.0
                ],
                [
                    310.0,
                    273.0
                ],
                [
                    306.0,
                    273.0
                ],
                [
                    306.0,
                    272.0
                ],
                [
                    304.0,
                    272.0
                ],
                [
                    304.0,
                    271.0
                ],
                [
                    303.0,
                    271.0
                ],
                [
                    303.0,
                    268.0
                ],
                [
                    304.0,
                    268.0
                ],
                [
                    304.0,
                    264.0
                ],
                [
                    303.0,
                    264.0
                ],
                [
                    303.0,
                    260.0
                ],
                [
                    302.0,
                    260.0
                ],
                [
                    302.0,
                    259.0
                ],
                [
                    300.0,
                    259.0
                ],
                [
                    300.0,
                    258.0
                ],
                [
                    295.0,
                    258.0
                ],
                [
                    295.0,
                    257.0
                ],
                [
                    286.0,
                    257.0
                ],
                [
                    286.0,
                    256.0
                ],
                [
                    261.0,
                    256.0
                ],
                [
                    261.0,
                    255.0
                ],
                [
                    258.0,
                    255.0
                ],
                [
                    258.0,
                    256.0
                ],
                [
                    256.0,
                    256.0
                ],
                [
                    256.0,
                    255.0
                ],
                [
                    252.0,
                    255.0
                ],
                [
                    252.0,
                    254.0
                ],
                [
                    248.0,
                    254.0
                ],
                [
                    248.0,
                    255.0
                ],
                [
                    246.0,
                    255.0
                ],
                [
                    246.0,
                    254.0
                ],
                [
                    229.0,
                    254.0
                ],
                [
                    229.0,
                    253.0
                ],
                [
                    223.0,
                    253.0
                ],
                [
                    223.0,
                    252.0
                ],
                [
                    217.0,
                    252.0
                ],
                [
                    217.0,
                    251.0
                ],
                [
                    212.0,
                    251.0
                ],
                [
                    212.0,
                    250.0
                ],
                [
                    205.0,
                    250.0
                ],
                [
                    205.0,
                    249.0
                ],
                [
                    197.0,
                    249.0
                ],
                [
                    197.0,
                    248.0
                ],
                [
                    191.0,
                    248.0
                ],
                [
                    191.0,
                    247.0
                ],
                [
                    184.0,
                    247.0
                ],
                [
                    184.0,
                    246.0
                ],
                [
                    176.0,
                    246.0
                ],
                [
                    176.0,
                    245.0
                ],
                [
                    171.0,
                    245.0
                ],
                [
                    171.0,
                    244.0
                ],
                [
                    163.0,
                    244.0
                ],
                [
                    163.0,
                    243.0
                ],
                [
                    156.0,
                    243.0
                ],
                [
                    156.0,
                    242.0
                ],
                [
                    146.0,
                    242.0
                ],
                [
                    146.0,
                    241.0
                ],
                [
                    139.0,
                    241.0
                ],
                [
                    139.0,
                    240.0
                ],
                [
                    130.0,
                    240.0
                ],
                [
                    130.0,
                    239.0
                ],
                [
                    121.0,
                    239.0
                ],
                [
                    121.0,
                    238.0
                ],
                [
                    115.0,
                    238.0
                ],
                [
                    115.0,
                    237.0
                ],
                [
                    108.0,
                    237.0
                ],
                [
                    108.0,
                    236.0
                ],
                [
                    100.0,
                    236.0
                ],
                [
                    100.0,
                    235.0
                ],
                [
                    94.0,
                    235.0
                ],
                [
                    94.0,
                    234.0
                ],
                [
                    85.0,
                    234.0
                ],
                [
                    85.0,
                    233.0
                ],
                [
                    77.0,
                    233.0
                ],
                [
                    77.0,
                    232.0
                ],
                [
                    70.0,
                    232.0
                ],
                [
                    70.0,
                    231.0
                ],
                [
                    61.0,
                    231.0
                ],
                [
                    61.0,
                    230.0
                ],
                [
                    52.0,
                    230.0
                ],
                [
                    52.0,
                    229.0
                ],
                [
                    38.0,
                    229.0
                ],
                [
                    38.0,
                    230.0
                ],
                [
                    36.0,
                    230.0
                ],
                [
                    36.0,
                    229.0
                ],
                [
                    34.0,
                    229.0
                ],
                [
                    34.0,
                    230.0
                ],
                [
                    32.0,
                    230.0
                ],
                [
                    32.0,
                    229.0
                ],
                [
                    30.0,
                    229.0
                ],
                [
                    30.0,
                    230.0
                ],
                [
                    23.0,
                    230.0
                ],
                [
                    23.0,
                    229.0
                ],
                [
                    22.0,
                    229.0
                ],
                [
                    22.0,
                    230.0
                ],
                [
                    20.0,
                    230.0
                ],
                [
                    20.0,
                    229.0
                ],
                [
                    19.0,
                    229.0
                ],
                [
                    19.0,
                    230.0
                ],
                [
                    12.0,
                    230.0
                ],
                [
                    12.0,
                    229.0
                ],
                [
                    3.0,
                    229.0
                ],
                [
                    202.0,
                    424.0
                ],
                [
                    202.0,
                    425.0
                ],
                [
                    201.0,
                    425.0
                ],
                [
                    201.0,
                    426.0
                ],
                [
                    207.0,
                    426.0
                ],
                [
                    207.0,
                    424.0
                ],
                [
                    202.0,
                    424.0
                ]
            ],
            "group_id": null,
            "group_ids": [
                null
            ],
            "flags": {}
        }
    ]
}