{
    "text": [
        "Locate the construction vehicle that has a big, dark frame and a long arm.",
        "Find the engineering machine characterized by its sizable, dark body and elongated arm.",
        "Spot the vehicle used in engineering with a large, dark structure and a protruding arm."
    ],
    "is_sentence": true,
    "shapes": [
        {
            "label": "target",
            "labels": [
                "target"
            ],
            "shape_type": "polygon",
            "image_name": "lisat_gres_000000034912.jpg",
            "points": [
                [
                    372.0,
                    470.0
                ],
                [
                    372.0,
                    471.0
                ],
                [
                    367.0,
                    471.0
                ],
                [
                    367.0,
                    472.0
                ],
                [
                    366.0,
                    472.0
                ],
                [
                    366.0,
                    473.0
                ],
                [
                    364.0,
                    473.0
                ],
                [
                    364.0,
                    474.0
                ],
                [
                    362.0,
                    474.0
                ],
                [
                    362.0,
                    475.0
                ],
                [
                    360.0,
                    475.0
                ],
                [
                    360.0,
                    476.0
                ],
                [
                    358.0,
                    476.0
                ],
                [
                    358.0,
                    477.0
                ],
                [
                    357.0,
                    477.0
                ],
                [
                    357.0,
                    478.0
                ],
                [
                    356.0,
                    478.0
                ],
                [
                    356.0,
                    479.0
                ],
                [
                    355.0,
                    479.0
                ],
                [
                    355.0,
                    481.0
                ],
                [
                    356.0,
                    481.0
                ],
                [
                    356.0,
                    483.0
                ],
                [
                    357.0,
                    483.0
                ],
                [
                    357.0,
                    485.0
                ],
                [
                    356.0,
                    485.0
                ],
                [
                    356.0,
                    486.0
                ],
                [
                    355.0,
                    486.0
                ],
                [
                    355.0,
                    487.0
                ],
                [
                    353.0,
                    487.0
                ],
                [
                    353.0,
                    488.0
                ],
                [
                    352.0,
                    488.0
                ],
                [
                    352.0,
                    489.0
                ],
                [
                    350.0,
                    489.0
                ],
                [
                    350.0,
                    490.0
                ],
                [
                    348.0,
                    490.0
                ],
                [
                    348.0,
                    491.0
                ],
                [
                    346.0,
                    491.0
                ],
                [
                    346.0,
                    492.0
                ],
                [
                    344.0,
                    492.0
                ],
                [
                    344.0,
                    493.0
                ],
                [
                    342.0,
                    493.0
                ],
                [
                    342.0,
                    494.0
                ],
                [
                    341.0,
                    494.0
                ],
                [
                    341.0,
                    495.0
                ],
                [
                    339.0,
                    495.0
                ],
                [
                    339.0,
                    496.0
                ],
                [
                    338.0,
                    496.0
                ],
                [
                    338.0,
                    497.0
                ],
                [
                    336.0,
                    497.0
                ],
                [
                    336.0,
                    499.0
                ],
                [
                    335.0,
                    499.0
                ],
                [
                    335.0,
                    500.0
                ],
                [
                    336.0,
                    500.0
                ],
                [
                    336.0,
                    502.0
                ],
                [
                    338.0,
                    502.0
                ],
                [
                    338.0,
                    503.0
                ],
                [
                    339.0,
                    503.0
                ],
                [
                    339.0,
                    502.0
                ],
                [
                    341.0,
                    502.0
                ],
                [
                    341.0,
                    501.0
                ],
                [
                    343.0,
                    501.0
                ],
                [
                    343.0,
                    500.0
                ],
                [
                    345.0,
                    500.0
                ],
                [
                    345.0,
                    499.0
                ],
                [
                    347.0,
                    499.0
                ],
                [
                    347.0,
                    498.0
                ],
                [
                    349.0,
                    498.0
                ],
                [
                    349.0,
                    497.0
                ],
                [
                    351.0,
                    497.0
                ],
                [
                    351.0,
                    496.0
                ],
                [
                    353.0,
                    496.0
                ],
                [
                    353.0,
                    495.0
                ],
                [
                    355.0,
                    495.0
                ],
                [
                    355.0,
                    494.0
                ],
                [
                    357.0,
                    494.0
                ],
                [
                    357.0,
                    493.0
                ],
                [
                    359.0,
                    493.0
                ],
                [
                    359.0,
                    492.0
                ],
                [
                    365.0,
                    492.0
                ],
                [
                    365.0,
                    493.0
                ],
                [
                    367.0,
                    493.0
                ],
                [
                    367.0,
                    494.0
                ],
                [
                    368.0,
                    494.0
                ],
                [
                    368.0,
                    495.0
                ],
                [
                    369.0,
                    495.0
                ],
                [
                    369.0,
                    496.0
                ],
                [
                    370.0,
                    496.0
                ],
                [
                    370.0,
                    498.0
                ],
                [
                    371.0,
                    498.0
                ],
                [
                    371.0,
                    500.0
                ],
                [
                    372.0,
                    500.0
                ],
                [
                    372.0,
                    501.0
                ],
                [
                    373.0,
                    501.0
                ],
                [
                    373.0,
                    503.0
                ],
                [
                    374.0,
                    503.0
                ],
                [
                    374.0,
                    504.0
                ],
                [
                    375.0,
                    504.0
                ],
                [
                    375.0,
                    506.0
                ],
                [
                    376.0,
                    506.0
                ],
                [
                    376.0,
                    507.0
                ],
                [
                    377.0,
                    507.0
                ],
                [
                    377.0,
                    509.0
                ],
                [
                    378.0,
                    509.0
                ],
                [
                    378.0,
                    510.0
                ],
                [
                    379.0,
                    510.0
                ],
                [
                    379.0,
                    512.0
                ],
                [
                    400.0,
                    512.0
                ],
                [
                    400.0,
                    510.0
                ],
                [
                    401.0,
                    510.0
                ],
                [
                    401.0,
                    509.0
                ],
                [
                    402.0,
                    509.0
                ],
                [
                    402.0,
                    507.0
                ],
                [
                    401.0,
                    507.0
                ],
                [
                    401.0,
                    505.0
                ],
                [
                    400.0,
                    505.0
                ],
                [
                    400.0,
                    502.0
                ],
                [
                    402.0,
                    502.0
                ],
                [
                    402.0,
                    503.0
                ],
                [
                    405.0,
                    503.0
                ],
                [
                    405.0,
                    504.0
                ],
                [
                    407.0,
                    504.0
                ],
                [
                    407.0,
                    505.0
                ],
                [
                    410.0,
                    505.0
                ],
                [
                    410.0,
                    506.0
                ],
                [
                    412.0,
                    506.0
                ],
                [
                    412.0,
                    505.0
                ],
                [
                    414.0,
                    505.0
                ],
                [
                    414.0,
                    504.0
                ],
                [
                    416.0,
                    504.0
                ],
                [
                    416.0,
                    500.0
                ],
                [
                    415.0,
                    500.0
                ],
                [
                    415.0,
                    499.0
                ],
                [
                    414.0,
                    499.0
                ],
                [
                    414.0,
                    497.0
                ],
                [
                    413.0,
                    497.0
                ],
                [
                    413.0,
                    496.0
                ],
                [
                    412.0,
                    496.0
                ],
                [
                    412.0,
                    495.0
                ],
                [
                    410.0,
                    495.0
                ],
                [
                    410.0,
                    494.0
                ],
                [
                    409.0,
                    494.0
                ],
                [
                    409.0,
                    493.0
                ],
                [
                    407.0,
                    493.0
                ],
                [
                    407.0,
                    492.0
                ],
                [
                    405.0,
                    492.0
                ],
                [
                    405.0,
                    491.0
                ],
                [
                    403.0,
                    491.0
                ],
                [
                    403.0,
                    490.0
                ],
                [
                    402.0,
                    490.0
                ],
                [
                    402.0,
                    489.0
                ],
                [
                    400.0,
                    489.0
                ],
                [
                    400.0,
                    488.0
                ],
                [
                    397.0,
                    488.0
                ],
                [
                    397.0,
                    487.0
                ],
                [
                    394.0,
                    487.0
                ],
                [
                    394.0,
                    486.0
                ],
                [
                    392.0,
                    486.0
                ],
                [
                    392.0,
                    485.0
                ],
                [
                    390.0,
                    485.0
                ],
                [
                    390.0,
                    484.0
                ],
                [
                    389.0,
                    484.0
                ],
                [
                    389.0,
                    483.0
                ],
                [
                    388.0,
                    483.0
                ],
                [
                    388.0,
                    482.0
                ],
                [
                    386.0,
                    482.0
                ],
                [
                    386.0,
                    479.0
                ],
                [
                    385.0,
                    479.0
                ],
                [
                    385.0,
                    478.0
                ],
                [
                    383.0,
                    478.0
                ],
                [
                    383.0,
                    477.0
                ],
                [
                    382.0,
                    477.0
                ],
                [
                    382.0,
                    476.0
                ],
                [
                    381.0,
                    476.0
                ],
                [
                    381.0,
                    475.0
                ],
                [
                    380.0,
                    475.0
                ],
                [
                    380.0,
                    474.0
                ],
                [
                    379.0,
                    474.0
                ],
                [
                    379.0,
                    473.0
                ],
                [
                    378.0,
                    473.0
                ],
                [
                    378.0,
                    472.0
                ],
                [
                    376.0,
                    472.0
                ],
                [
                    376.0,
                    471.0
                ],
                [
                    373.0,
                    471.0
                ],
                [
                    373.0,
                    470.0
                ],
                [
                    372.0,
                    470.0
                ]
            ],
            "group_id": null,
            "group_ids": [
                null
            ],
            "flags": {}
        }
    ]
}